django_prune_uploads-0.3.1.dist-info/licenses/LICENSE
prune_uploads/__init__.py
prune_uploads/management/__init__.py
prune_uploads/management/commands/__init__.py
prune_uploads/management/commands/prune_uploads.py
django_prune_uploads-0.3.1.dist-info/METADATA
django_prune_uploads-0.3.1.dist-info/WHEEL
django_prune_uploads-0.3.1.dist-info/top_level.txt
django_prune_uploads-0.3.1.dist-info/RECORD
