Metadata-Version: 2.4
Name: django_prune_uploads
Version: 0.3.1
Summary: Prune and maintain file uploads
Home-page: https://github.com/matthiask/django-prune-uploads/
Author: Matthias Kestenholz
Author-email: mk@feinheit.ch
License: MIT
Platform: OS Independent
Classifier: Development Status :: 4 - Beta
Classifier: Environment :: Web Environment
Classifier: Framework :: Django
Classifier: Intended Audience :: Developers
Classifier: License :: OSI Approved :: BSD License
Classifier: License :: OSI Approved :: MIT License
Classifier: Operating System :: OS Independent
Classifier: Programming Language :: Python
Classifier: Programming Language :: Python :: 3
Classifier: Topic :: Internet :: WWW/HTTP :: Dynamic Content
Classifier: Topic :: Software Development
Classifier: Topic :: Software Development :: Libraries :: Application Frameworks
License-File: LICENSE
Provides-Extra: s3
Requires-Dist: boto3; extra == "s3"
Dynamic: license-file
